llm_intercept/__init__.py
llm_intercept/admin.py
llm_intercept/app.py
llm_intercept/cli.py
llm_intercept/database.py
llm_intercept/models.py
llm_intercept/proxy.py
llm_intercept-1.0.0.dist-info/licenses/LICENSE
llm_intercept-1.0.0.dist-info/METADATA
llm_intercept-1.0.0.dist-info/WHEEL
llm_intercept-1.0.0.dist-info/entry_points.txt
llm_intercept-1.0.0.dist-info/top_level.txt
llm_intercept-1.0.0.dist-info/RECORD
